oocana-0.18.11.dist-info/METADATA
oocana-0.18.11.dist-info/WHEEL
oocana-0.18.11.dist-info/entry_points.txt
oocana/__init__.py
oocana/context.py
oocana/credential.py
oocana/data.py
oocana/extra.py
oocana/handle.py
oocana/internal.py
oocana/mainframe.py
oocana/preview.py
oocana/schema.py
oocana/serialization.py
oocana/service.py
oocana/throttler.py
oocana-0.18.11.dist-info/RECORD
