Metadata-Version: 2.1
Name: oocana
Version: 0.18.11
Summary: python implement of oocana to give a context for oocana block
License: MIT
Requires-Python: >=3.9
Requires-Dist: paho-mqtt>=2
Requires-Dist: simplejson>=3.19.2
